{
	"name" : "sequential_pipeline_project",
	"projectDescription" : "Test project created by xpresso platform",
	"owner" : {
		"uid": "Asahu2"
	},
    "developers" : ["ArunangsuSa2"],
	"components" : [
		{
			"name" : "download_task",
			"type" : "datascience-job",
			"flavor" : "python"
		},
		{
			"name" : "echo_task",
			"type" : "datascience-job",
			"flavor" : "python"
		}
	],
	"pipelines" : [
		{
			"name" : "sequential_pipeline",
			"components" : ["download_task", "echo_task"],
			"declarative_json" : "seq-pipeline-def.json"
		}
	]
}
